darcyai/__init__.py
darcyai/config.py
darcyai/config_registry.py
darcyai/configurable.py
darcyai/cyclic_toposort.py
darcyai/event_emitter.py
darcyai/file_stream.py
darcyai/log.py
darcyai/perception_object_model.py
darcyai/pipeline.py
darcyai/processing_engine.py
darcyai/serializable.py
darcyai/stream_data.py
darcyai/utils.py
darcyai/input/__init__.py
darcyai/input/camera_stream.py
darcyai/input/input_multi_stream.py
darcyai/input/input_stream.py
darcyai/input/video_file_stream.py
darcyai/input/video_stream_data.py
darcyai/integration_tests/__init__.py
darcyai/integration_tests/tests.py
darcyai/output/__init__.py
darcyai/output/csv_output_stream.py
darcyai/output/json_output_stream.py
darcyai/output/live_feed_stream.py
darcyai/output/output_stream.py
darcyai/output/rest_api_stream.py
darcyai/perceptor/__init__.py
darcyai/perceptor/detected_class.py
darcyai/perceptor/detected_object.py
darcyai/perceptor/image_classification_perceptor.py
darcyai/perceptor/multi_platform_perceptor_base.py
darcyai/perceptor/object_detection_perceptor.py
darcyai/perceptor/people_perceptor.py
darcyai/perceptor/people_perceptor_base.py
darcyai/perceptor/people_perceptor_pom.py
darcyai/perceptor/perceptor.py
darcyai/perceptor/perceptor_node.py
darcyai/perceptor/perceptor_utils.py
darcyai/perceptor/processor.py
darcyai/perceptor/coral/__init__.py
darcyai/perceptor/coral/coral_perceptor_base.py
darcyai/perceptor/coral/image_classification_perceptor.py
darcyai/perceptor/coral/object_detection_perceptor.py
darcyai/perceptor/coral/people_perceptor.py
darcyai/perceptor/coral/models/posenet.tflite
darcyai/perceptor/cpu/__init__.py
darcyai/perceptor/cpu/cpu_perceptor_base.py
darcyai/perceptor/cpu/image_classification_perceptor.py
darcyai/perceptor/cpu/object_detection_perceptor.py
darcyai/perceptor/cpu/people_perceptor.py
darcyai/perceptor/cpu/models/posenet.tflite
darcyai/perceptor/posenet_lib/aarch64/linux/posenet_decoder.so
darcyai/perceptor/posenet_lib/arm64/darwin/posenet_decoder.so
darcyai-2.0.3.dist-info/LICENSE
darcyai-2.0.3.dist-info/METADATA
darcyai-2.0.3.dist-info/WHEEL
darcyai-2.0.3.dist-info/top_level.txt
darcyai-2.0.3.dist-info/RECORD
