Metadata-Version: 2.1
Name: darcyai
Version: 2.0.3
Summary: DarcyAI Library
Home-page: https://github.com/darcyai/darcyai
Author: darcy.ai
Author-email: info@darcy.ai
Project-URL: Documentation, https://darcyai.github.io/darcyai/
Project-URL: Bug Reports, https://github.com/darcyai/darcyai/issues
Project-URL: Source Code, https://github.com/darcyai/darcyai
Keywords: darcy,darcyai
Classifier: Development Status :: 2 - Pre-Alpha
Classifier: Intended Audience :: Developers
Requires-Python: >=3.6.9
License-File: LICENSE
Requires-Dist: pillow (==8.3.2)
Requires-Dist: imutils (==0.5.4)
Requires-Dist: pytest (==6.2.5)
Requires-Dist: flask (==2.0.2)
Requires-Dist: requests (==2.26.0)
Requires-Dist: logging-json (==0.2.1)
